eimerdb/__init__.py
eimerdb/abstract_db_instance.py
eimerdb/eimerdb_constants.py
eimerdb/functions.py
eimerdb/instance.py
eimerdb/instance_query_worker.py
eimerdb/py.typed
eimerdb/query.py
ssb_eimerdb-0.2.5.dist-info/LICENSE
ssb_eimerdb-0.2.5.dist-info/METADATA
ssb_eimerdb-0.2.5.dist-info/WHEEL
ssb_eimerdb-0.2.5.dist-info/RECORD
