Metadata-Version: 2.3
Name: ssb-eimerdb
Version: 0.2.5
Summary: EimerDB
License: MIT
Author: Stian Elisenberg
Author-email: seg@ssb.no
Maintainer: Statistics Norway, Data enablement Department (724)
Requires-Python: >=3.10,<4.0
Classifier: Development Status :: 4 - Beta
Classifier: License :: OSI Approved :: MIT License
Classifier: Programming Language :: Python :: 3
Classifier: Programming Language :: Python :: 3.10
Classifier: Programming Language :: Python :: 3.11
Classifier: Programming Language :: Python :: 3.12
Classifier: Programming Language :: Python :: 3.13
Requires-Dist: docstring-inheritance (>=2.2.0)
Requires-Dist: duckdb (>=1.0.0)
Requires-Dist: gcsfs (>=2025.7.0)
Requires-Dist: google-cloud-storage (>=2.15.0)
Requires-Dist: pandas (>=2.2.1)
Requires-Dist: polars (>=1.26.0)
Requires-Dist: pyarrow (>=17.0.0)
Project-URL: Changelog, https://github.com/statisticsnorway/ssb-eimerdb/releases
Project-URL: Documentation, https://statisticsnorway.github.io/ssb-eimerdb
Project-URL: Homepage, https://github.com/statisticsnorway/ssb-eimerdb
Project-URL: Repository, https://github.com/statisticsnorway/ssb-eimerdb
